[
    {
        "filename": "tgdev309.zip",
        "description_offset": 0,
        "description_len": 0,
        "size_bytes": 75906,
        "ul_date": 1774829911,
        "file_date": 1772618265,
        "dl_date": 0,
        "status": 12,
        "downloads": 0,
        "uploader": "Gemini",
        "password_crc": 0
    },
    {
        "filename": "bdays200.zip",
        "description_offset": 0,
        "description_len": 0,
        "size_bytes": 3087406,
        "ul_date": 1774829910,
        "file_date": 1774501552,
        "dl_date": 0,
        "status": 12,
        "downloads": 0,
        "uploader": "Gemini",
        "password_crc": 0
    },
    {
        "filename": "fdtg_300.zip",
        "description_offset": 0,
        "description_len": 0,
        "size_bytes": 13276,
        "ul_date": 1774829910,
        "file_date": 1772618265,
        "dl_date": 0,
        "status": 12,
        "downloads": 0,
        "uploader": "Gemini",
        "password_crc": 0
    },
    {
        "filename": "hstat200.zip",
        "description_offset": 0,
        "description_len": 0,
        "size_bytes": 14973,
        "ul_date": 1774829910,
        "file_date": 1772618265,
        "dl_date": 0,
        "status": 12,
        "downloads": 0,
        "uploader": "Gemini",
        "password_crc": 0
    },
    {
        "filename": "tg2309g2.zip",
        "description_offset": 0,
        "description_len": 0,
        "size_bytes": 687413,
        "ul_date": 1774829910,
        "file_date": 1772618265,
        "dl_date": 0,
        "status": 12,
        "downloads": 0,
        "uploader": "Gemini",
        "password_crc": 0
    },
    {
        "filename": "tg309sp3.zip",
        "description_offset": 0,
        "description_len": 0,
        "size_bytes": 282343,
        "ul_date": 1774829910,
        "file_date": 1772618265,
        "dl_date": 0,
        "status": 12,
        "downloads": 0,
        "uploader": "Gemini",
        "password_crc": 0
    },
    {
        "filename": "tg309sp4.zip",
        "description_offset": 0,
        "description_len": 0,
        "size_bytes": 583444,
        "ul_date": 1774829910,
        "file_date": 1772618265,
        "dl_date": 0,
        "status": 12,
        "downloads": 0,
        "uploader": "Gemini",
        "password_crc": 0
    },
    {
        "filename": "tg_302.zip",
        "description_offset": 0,
        "description_len": 0,
        "size_bytes": 568114,
        "ul_date": 1774829910,
        "file_date": 1772618265,
        "dl_date": 0,
        "status": 12,
        "downloads": 0,
        "uploader": "Gemini",
        "password_crc": 0
    },
    {
        "filename": "tg_309g2.zip",
        "description_offset": 0,
        "description_len": 0,
        "size_bytes": 655970,
        "ul_date": 1774829910,
        "file_date": 1772618265,
        "dl_date": 0,
        "status": 12,
        "downloads": 0,
        "uploader": "Gemini",
        "password_crc": 0
    },
    {
        "filename": "tg_upg32.zip",
        "description_offset": 0,
        "description_len": 0,
        "size_bytes": 22417,
        "ul_date": 1774829910,
        "file_date": 1772618265,
        "dl_date": 0,
        "status": 12,
        "downloads": 0,
        "uploader": "Gemini",
        "password_crc": 0
    },
    {
        "filename": "tgdev301.zip",
        "description_offset": 0,
        "description_len": 0,
        "size_bytes": 68596,
        "ul_date": 1774829911,
        "file_date": 1772618265,
        "dl_date": 0,
        "status": 12,
        "downloads": 0,
        "uploader": "Gemini",
        "password_crc": 0
    },
    {
        "filename": "tgnws310.zip",
        "description_offset": 0,
        "description_len": 0,
        "size_bytes": 86316,
        "ul_date": 1774829911,
        "file_date": 1772618265,
        "dl_date": 0,
        "status": 12,
        "downloads": 0,
        "uploader": "Gemini",
        "password_crc": 0
    },
    {
        "filename": "votef150.zip",
        "description_offset": 0,
        "description_len": 0,
        "size_bytes": 10416,
        "ul_date": 1774829911,
        "file_date": 1772618265,
        "dl_date": 0,
        "status": 12,
        "downloads": 0,
        "uploader": "Gemini",
        "password_crc": 0
    }
]